convergence/__init__.py
convergence/sdk.py
convergence/cli/__init__.py
convergence/cli/main.py
convergence/core/__init__.py
convergence/core/config.py
convergence/core/env_loader.py
convergence/core/llm_provider.py
convergence/core/protocols.py
convergence/core/registry.py
convergence/core/runtime.py
convergence/core/weave_logger.py
convergence/evaluators/__init__.py
convergence/evaluators/agents.py
convergence/evaluators/base.py
convergence/evaluators/code_quality.py
convergence/evaluators/json_structure.py
convergence/evaluators/text_quality.py
convergence/generator/__init__.py
convergence/generator/ai_powered_setup.py
convergence/generator/async_generation_utils.py
convergence/generator/constants.py
convergence/generator/custom_template_generator.py
convergence/generator/init_orchestrator.py
convergence/generator/interactive_setup.py
convergence/generator/natural_language_processor.py
convergence/generator/preset_templates.py
convergence/generator/template_selector.py
convergence/generator/templates/__init__.py
convergence/generator/templates/agent_runner_template.py
convergence/generator/templates/azure_chat_template.py
convergence/generator/templates/llm_chat_template.py
convergence/generator/templates/web_automation_template.py
convergence/legacy/__init__.py
convergence/legacy/models.py
convergence/legacy/store.py
convergence/legacy/trackers.py
convergence/optimization/__init__.py
convergence/optimization/api_caller.py
convergence/optimization/config_loader.py
convergence/optimization/config_validator.py
convergence/optimization/evaluator.py
convergence/optimization/evolution.py
convergence/optimization/models.py
convergence/optimization/response_utils.py
convergence/optimization/rl_optimizer.py
convergence/optimization/runner.py
convergence/optimization/test_case_evolution.py
convergence/optimization/adapters/__init__.py
convergence/optimization/adapters/agno_agent.py
convergence/optimization/adapters/azure.py
convergence/optimization/adapters/browserbase.py
the_convergence-0.1.7.dist-info/licenses/LICENSE
the_convergence-0.1.7.dist-info/METADATA
the_convergence-0.1.7.dist-info/WHEEL
the_convergence-0.1.7.dist-info/entry_points.txt
the_convergence-0.1.7.dist-info/top_level.txt
the_convergence-0.1.7.dist-info/RECORD
