Metadata-Version: 2.4
Name: the-convergence
Version: 0.1.7
Summary: API Optimization Framework powered by evolutionary algorithms, multi-armed bandits, and agent societies
Author-email: Aria Han <aria@persistos.co>, Shreyash Hamal <shrey@persistos.co>, Myat Pyae Paing <paing@persistos.co>
Maintainer-email: Aria Han <aria@persistos.co>, Shreyash Hamal <shrey@persistos.co>, Myat Pyae Paing <paing@persistos.co>
License: Apache-2.0
Project-URL: Homepage, https://github.com/persist-os/the-convergence
Project-URL: Documentation, https://github.com/persist-os/the-convergence#readme
Project-URL: Repository, https://github.com/persist-os/the-convergence
Project-URL: Issues, https://github.com/persist-os/the-convergence/issues
Project-URL: Changelog, https://github.com/persist-os/the-convergence/blob/main/CHANGELOG.md
Keywords: optimization,api,evolutionary-algorithms,multi-armed-bandits,reinforcement-learning,agent-society,llm-optimization,parameter-tuning,a-b-testing,machine-learning
Classifier: Development Status :: 3 - Alpha
Classifier: Intended Audience :: Developers
Classifier: Intended Audience :: Science/Research
Classifier: Topic :: Software Development :: Libraries :: Python Modules
Classifier: Topic :: Scientific/Engineering :: Artificial Intelligence
Classifier: License :: OSI Approved :: Apache Software License
Classifier: Programming Language :: Python :: 3
Classifier: Programming Language :: Python :: 3.11
Classifier: Programming Language :: Python :: 3.12
Classifier: Operating System :: OS Independent
Classifier: Typing :: Typed
Requires-Python: >=3.11
License-File: LICENSE
Requires-Dist: pydantic>=2.0.0
Requires-Dist: pydantic-settings>=2.0.0
Requires-Dist: typer>=0.9.0
Requires-Dist: pyyaml>=6.0.0
Requires-Dist: rich>=13.0.0
Requires-Dist: diagrams
Requires-Dist: httpx>=0.25.0
Requires-Dist: tenacity>=8.0.0
Requires-Dist: numpy>=1.24.0
Requires-Dist: scipy>=1.10.0
Requires-Dist: aiosqlite>=0.19.0
Requires-Dist: aiofiles>=23.0.0
Requires-Dist: weave>=0.50.0
Requires-Dist: litellm>=1.0.0
Requires-Dist: python-dotenv>=1.0.0
Requires-Dist: pluggy>=1.3.0
Provides-Extra: agents
Requires-Dist: transformers>=4.40.0; extra == "agents"
Requires-Dist: torch>=2.0.0; extra == "agents"
Requires-Dist: trl>=0.8.0; extra == "agents"
Requires-Dist: peft>=0.10.0; extra == "agents"
Requires-Dist: datasets>=2.18.0; extra == "agents"
Requires-Dist: accelerate>=0.27.0; extra == "agents"
Requires-Dist: litellm>=1.0.0; extra == "agents"
Provides-Extra: llm
Requires-Dist: langgraph>=0.0.1; extra == "llm"
Requires-Dist: litellm>=1.0.0; extra == "llm"
Provides-Extra: reddit
Requires-Dist: asyncpraw>=7.8.0; extra == "reddit"
Requires-Dist: agno>=2.1.8; extra == "reddit"
Provides-Extra: all
Requires-Dist: the-convergence[agents,llm,reddit]; extra == "all"
Provides-Extra: dev
Requires-Dist: pytest>=7.0.0; extra == "dev"
Requires-Dist: pytest-asyncio>=0.21.0; extra == "dev"
Requires-Dist: hypothesis>=6.0.0; extra == "dev"
Requires-Dist: ruff>=0.1.0; extra == "dev"
Requires-Dist: mypy>=1.0.0; extra == "dev"
Requires-Dist: mkdocs>=1.5.0; extra == "dev"
Requires-Dist: mkdocs-material>=9.0.0; extra == "dev"
Dynamic: license-file
